magnumnp/__init__.py
magnumnp/common/__init__.py
magnumnp/common/constants.py
magnumnp/common/io.py
magnumnp/common/logging.py
magnumnp/common/material.py
magnumnp/common/mesh.py
magnumnp/common/state.py
magnumnp/common/tabulate.py
magnumnp/common/time_interpolator.py
magnumnp/common/timer.py
magnumnp/common/utils.py
magnumnp/field_terms/__init__.py
magnumnp/field_terms/anisotropy.py
magnumnp/field_terms/demag.py
magnumnp/field_terms/demagPBC.py
magnumnp/field_terms/demag_nonequidistant.py
magnumnp/field_terms/dmi.py
magnumnp/field_terms/exchange.py
magnumnp/field_terms/external.py
magnumnp/field_terms/field_terms.py
magnumnp/field_terms/magnetoelastic.py
magnumnp/field_terms/oersted.py
magnumnp/field_terms/rkky.py
magnumnp/field_terms/rux.py
magnumnp/field_terms/spintorque.py
magnumnp/field_terms/thermal.py
magnumnp/field_terms/vector_potential.py
magnumnp/linear_elasticity/__init__.py
magnumnp/linear_elasticity/bcs.py
magnumnp/linear_elasticity/deriv_term_compiler.py
magnumnp/linear_elasticity/stiffness_matrices.py
magnumnp/linear_elasticity/strain.py
magnumnp/linear_elasticity/stress.py
magnumnp/linear_elasticity/utils.py
magnumnp/loggers/__init__.py
magnumnp/loggers/field_logger.py
magnumnp/loggers/logger.py
magnumnp/loggers/scalar_logger.py
magnumnp/solvers/LBFGS.py
magnumnp/solvers/__init__.py
magnumnp/solvers/eigensolver.py
magnumnp/solvers/llg.py
magnumnp/solvers/llg_with_le_solver.py
magnumnp/solvers/minimize.py
magnumnp/solvers/ohm_solver.py
magnumnp/solvers/steepest_descent.py
magnumnp/solvers/string.py
magnumnp/solvers/ode_solvers/__init__.py
magnumnp/solvers/ode_solvers/heun.py
magnumnp/solvers/ode_solvers/rkf45.py
magnumnp/solvers/ode_solvers/rkf56.py
magnumnp/solvers/ode_solvers/scipy_ode.py
magnumnp/solvers/ode_solvers/scipy_odeint.py
magnumnp/solvers/ode_solvers/torchdiffeq.py
magnumnp/utils/__init__.py
magnumnp/utils/coil.py
magnumnp/utils/imaging_tools.py
magnumnp/utils/logging_helpers.py
magnumnp/utils/misc.py
magnumnp/utils/voronoi.py
magnumnp-2.1.0.dist-info/licenses/AUTHORS
magnumnp-2.1.0.dist-info/licenses/LICENSE
magnumnp-2.1.0.dist-info/METADATA
magnumnp-2.1.0.dist-info/WHEEL
magnumnp-2.1.0.dist-info/top_level.txt
magnumnp-2.1.0.dist-info/RECORD
