Metadata-Version: 2.4
Name: magnumnp
Version: 2.1.0
Summary: magnum.np finite-difference package for the solution of micromagnetic problems
Home-page: http://gitlab.com/magnum.np/magnum.np
Author: Florian Bruckner
Author-email: florian.bruckner@univie.ac.at
Project-URL: Documentation, https://magnum.np.gitlab.io/magnum.np/
Project-URL: Changelog, https://gitlab.com/magnum.np/magnum.np/blob/main/CHANGELOG
License-File: LICENSE
License-File: AUTHORS
Requires-Dist: numpy
Requires-Dist: pyvista
Requires-Dist: scipy
Requires-Dist: setproctitle
Requires-Dist: torch
Requires-Dist: torchdiffeq
Requires-Dist: xitorch
Requires-Dist: tqdm
Dynamic: author
Dynamic: author-email
Dynamic: description
Dynamic: description-content-type
Dynamic: home-page
Dynamic: license-file
Dynamic: project-url
Dynamic: requires-dist
Dynamic: summary
